businessowner_retriever.py
businessowner_retriever-2.0.1.dist-info/entry_points.txt
businessowner_retriever-2.0.1.dist-info/WHEEL
businessowner_retriever-2.0.1.dist-info/METADATA
businessowner_retriever-2.0.1.dist-info/RECORD
