Metadata-Version: 2.1
Name: businessowner-retriever
Version: 2.0.1
Summary: Tool to retrieve list of Vietnamese registered business owners.
Home-page: https://bitbucket.org/hongquan/businessowner_retriever
License: GPL-3.0-or-later
Keywords: Vietnamese,business
Author: Nguyễn Hồng Quân
Author-email: ng.hong.quan@gmail.com
Requires-Python: >=3.7,<4.0
Classifier: Environment :: Console
Classifier: Intended Audience :: Legal Industry
Classifier: Intended Audience :: Manufacturing
Classifier: License :: OSI Approved :: GNU General Public License v3 or later (GPLv3+)
Classifier: Programming Language :: Python :: 3
Classifier: Programming Language :: Python :: 3 :: Only
Classifier: Programming Language :: Python :: 3.7
Classifier: Programming Language :: Python :: 3.8
Requires-Dist: Logbook (>=1.5.2,<2.0.0)
Requires-Dist: click (>=7.0,<8.0)
Requires-Dist: colorama (>=0.4.1,<0.5.0)
Requires-Dist: named-enum (>=1.0.0,<2.0.0)
Requires-Dist: parsel (>=1.5.2,<2.0.0)
Requires-Dist: requests[socks] (>=2.22.0,<3.0.0)
Requires-Dist: terminaltables (>=3.1.0,<4.0.0)
Project-URL: Repository, https://bitbucket.org/hongquan/businessowner_retriever.git
